gyyre/__init__.py
gyyre/_code_gen/__init__.py
gyyre/_code_gen/_exec.py
gyyre/_code_gen/_llm.py
gyyre/_operator_impls/__init__.py
gyyre/_operator_impls/_sem_choose_llm.py
gyyre/_operator_impls/_sem_fillna_llm.py
gyyre/_operator_impls/_sem_fillna_llm_plus_model.py
gyyre/_operator_impls/_sem_select_llm.py
gyyre/_operator_impls/_with_sem_features_caafe.py
gyyre/_operators.py
gyyre/optimisers/__init__.py
gyyre/optimisers/_dag_summary.py
gyyre/optimisers/greedy.py
gyyre-0.0.1.dist-info/LICENSE
gyyre-0.0.1.dist-info/METADATA
gyyre-0.0.1.dist-info/WHEEL
gyyre-0.0.1.dist-info/RECORD
