Metadata-Version: 2.1
Name: gyyre
Version: 0.0.1
Summary: 
Author: Sebastian Schelter
Author-email: schelter@tu-berlin.de
Requires-Python: >=3.12,<4.0
Classifier: Programming Language :: Python :: 3
Classifier: Programming Language :: Python :: 3.12
Requires-Dist: graphviz (>=0.21,<0.22)
Requires-Dist: litellm (>=1.76.1,<2.0.0)
Requires-Dist: networkx (>=3.5,<4.0)
Requires-Dist: plotly (>=6.3.0,<7.0.0)
Requires-Dist: skrub (>=0.6.1,<0.7.0)
